{
	"1": {
		"id": "114001",
		"word": [
			{ "ar": "قُلۡ", "tl": "qul" },
			{ "ar": "أَعُوذُ", "tl": "a'udhu" },
			{ "ar": "بِرَبِّ", "tl": "birabbi" },
			{ "ar": "ٱلنَّاسِ", "tl": "al-nasi" }
		]
	},
	"2": {
		"id": "114002",
		"word": [
			{ "ar": "مَلِكِ", "tl": "maliki" },
			{ "ar": "ٱلنَّاسِ", "tl": "al-nasi" }
		]
	},
	"3": {
		"id": "114003",
		"word": [
			{ "ar": "إِلَٰهِ", "tl": "ilahi" },
			{ "ar": "ٱلنَّاسِ", "tl": "al-nasi" }
		]
	},
	"4": {
		"id": "114004",
		"word": [
			{ "ar": "مِن", "tl": "min" },
			{ "ar": "شَرِّ", "tl": "sharri" },
			{ "ar": "ٱلۡوَسۡوَاسِ", "tl": "al-waswasi" },
			{ "ar": "ٱلۡخَنَّاسِ", "tl": "al-khanasi" }
		]
	},
	"5": {
		"id": "114005",
		"word": [
			{ "ar": "ٱلَّذِي", "tl": "alladhi" },
			{ "ar": "يُوَسۡوِسُ", "tl": "yuwaswisu" },
			{ "ar": "فِي", "tl": "fi" },
			{ "ar": "صُدُورِ", "tl": "suduri" },
			{ "ar": "ٱلنَّاسِ", "tl": "al-nasi" }
		]
	},
	"6": {
		"id": "114006",
		"word": [
			{ "ar": "مِنَ", "tl": "mina" },
			{ "ar": "ٱلۡجِنَّةِ", "tl": "al-jinati" },
			{ "ar": "وَٱلنَّاسِ", "tl": "wal-nasi" }
		]
	}
}
