{
	"1": {
		"word": [
			{ "start": 1.15, "end": 1.68 },
			{ "start": 1.68, "end": 4.93 },
			{ "start": 4.93, "end": null }
		]
	},
	"2": {
		"word": [
			{ "start": 0.4, "end": 2.14 },
			{ "start": 2.14, "end": 3.6 },
			{ "start": 3.6, "end": 4.33 },
			{ "start": 4.33, "end": null }
		]
	},
	"3": {
		"word": [
			{ "start": 0.65, "end": 2.39 },
			{ "start": 2.39, "end": 4.14 },
			{ "start": 4.14, "end": 6.61 },
			{ "start": 6.61, "end": 8.28 },
			{ "start": 8.28, "end": null }
		]
	},
	"4": {
		"word": [
			{ "start": 0.4, "end": 2.24 },
			{ "start": 2.24, "end": 2.86 },
			{ "start": 2.86, "end": 5.17 },
			{ "start": 5.17, "end": 6.12 },
			{ "start": 6.12, "end": null }
		]
	},
	"5": {
		"word": [
			{ "start": 0.21, "end": 2.14 },
			{ "start": 2.14, "end": 3.99 },
			{ "start": 3.99, "end": 6.57 },
			{ "start": 6.57, "end": 8.3 },
			{ "start": 8.3, "end": null }
		]
	},
	"6": {
		"word": [
			{ "start": 0.55, "end": 1.58 },
			{ "start": 1.58, "end": 3.45 },
			{ "start": 3.45, "end": 4.7 },
			{ "start": 4.7, "end": null }
		]
	}
}
